{
  "name": "intelligent_rag_query",
  "description": "Query the intelligent RAG server",
  "parameters": {
    "type": "object",
    "properties": {
      "projectId": {
        "type": "string",
        "description": "The project ID to query against"
      },
      "thinkingDepth": {
        "type": "integer",
        "description": "Depth of thinking (1-4). Higher values use more sophisticated processing",
        "enum": [1, 2, 3, 4]
      },
      "query": {
        "type": "string",
        "description": "The query to send to the RAG server"
      }
    },
    "required": ["projectId", "query"]
  }
}